dcutils/__init__.py
dcutils/_utils/__init__.py
dcutils/_utils/file_manager.py
dcutils/dc_config.py
dcutils/static/__init__.py
dcutils/static/animations/__init__.py
dcutils/static/animations/flash/dragon.py
dcutils/static/animations/spine/dragon.py
dcutils/static/base.py
dcutils/static/islands/__init__.py
dcutils/static/islands/package.py
dcutils/static/localization/__init__.py
dcutils/static/platform_prefixes.py
dcutils/static/sounds/__init__.py
dcutils/static/sounds/config.py
dcutils/static/sounds/musics.py
dcutils/static/sprites/__init__.py
dcutils/static/sprites/chest.py
dcutils/static/sprites/dragon.py
dcutils/static/sprites/dragon_thumb.py
dcutils/tools/__init__.py
dcutils/tools/ai/base.py
dcutils/tools/ai/elements_detector.py
dcutils/tools/ai/phase_detector.py
dcutils/tools/calculators/__init__.py
dcutils/tools/calculators/dragon/__init__.py
dcutils/tools/calculators/dragon/attack_damage/__init__.py
dcutils/tools/calculators/dragon/attack_damage/config.py
dcutils/tools/calculators/dragon/dragon_rarities.py
dcutils/tools/calculators/dragon/status/__init__.py
dcutils/tools/calculators/dragon/status/config.py
dcutils/tools/calculators/elements/__init__.py
dcutils/tools/calculators/elements/config.py
dcutils/tools/calculators/food/__init__.py
dcutils/tools/calculators/food/config.py
dcutils/tools/calculators/old_battle_simulator.py
dcutils/tools/calculators/orb_recall/__init__.py
dcutils/tools/calculators/orb_recall/config.py
dcutils/tools/url_parser/__init__.py
dcutils/tools/url_parser/dragon.py
dragon_city_utils-2.1.1.dist-info/METADATA
dragon_city_utils-2.1.1.dist-info/WHEEL
dragon_city_utils-2.1.1.dist-info/RECORD
