Metadata-Version: 2.1
Name: dragon-city-utils
Version: 2.1.1
Summary: Dragon City Utils, a collection of tools and utilities for managing static assets and performing calculations related to the Dragon City game.
License: MIT
Author: Marcuth
Author-email: me@marcuth.dev
Requires-Python: >=3.12,<4.0
Classifier: License :: OSI Approved :: MIT License
Classifier: Programming Language :: Python :: 3
Classifier: Programming Language :: Python :: 3.12
Requires-Dist: httpx
Requires-Dist: keras
Requires-Dist: pillow
Requires-Dist: pydantic
Requires-Dist: python-filter
Requires-Dist: python-pathutil
Requires-Dist: tensorflow
